xrootdpyfs/__init__.py
xrootdpyfs/env.py
xrootdpyfs/fs.py
xrootdpyfs/opener.py
xrootdpyfs/utils.py
xrootdpyfs/xrdfile.py
xrootdpyfs-2.0.0.dist-info/AUTHORS
xrootdpyfs-2.0.0.dist-info/LICENSE
xrootdpyfs-2.0.0.dist-info/METADATA
xrootdpyfs-2.0.0.dist-info/WHEEL
xrootdpyfs-2.0.0.dist-info/entry_points.txt
xrootdpyfs-2.0.0.dist-info/top_level.txt
xrootdpyfs-2.0.0.dist-info/RECORD
