Metadata-Version: 2.1
Name: xrootdpyfs
Version: 2.0.0
Summary: XRootDPyFS is a PyFilesystem interface for XRootD.
Home-page: https://github.com/inveniosoftware/xrootdpyfs
Author: CERN
Author-email: info@inveniosoftware.org
License: BSD
Keywords: xrootdpyfs
Platform: any
Classifier: Programming Language :: Python :: 3
Classifier: Development Status :: 5 - Production/Stable
Classifier: Intended Audience :: Developers
Classifier: License :: OSI Approved :: BSD License
Classifier: Topic :: Utilities
Requires-Python: >=3.6
License-File: LICENSE
License-File: AUTHORS
Requires-Dist: fs <3.0,>=2.0.10
Requires-Dist: xrootd <6.0.0,>=5.0.0
Provides-Extra: tests
Requires-Dist: mock >=4.0.0 ; extra == 'tests'
Requires-Dist: pytest-black >=0.3.0 ; extra == 'tests'
Requires-Dist: pytest-invenio >=1.4.5 ; extra == 'tests'
Requires-Dist: Sphinx >=4.2.0 ; extra == 'tests'
